{
  "project_slug": "maestro-03-ratchada-rama-9",
  "collected_at": "2026-07-14",
  "source": "hipflat",
  "search_sale_url": "https://www.hipflat.co.th/en/search/sale/bangkok/condo?q=Maestro%2003%20Ratchada-Rama%209",
  "search_rent_url": "https://www.hipflat.co.th/en/search/rent/bangkok/condo?q=Maestro%2003%20Ratchada-Rama%209",
  "notes": "Hipflat harvest — verified only when public detail exposes priced offer + listing type. No fabricated fields. No Cloudflare bypass. PropertyHub/LivingInsider/DDproperty untouched.",
  "listings": []
}
