{
  "project_slug": "ideo-q-sukhumvit-36",
  "collected_at": "2026-07-14",
  "source": "propertyhub",
  "notes": "Harvested from PropertyHub public listing detail __NEXT_DATA__. verification_status=verified only when price present on detail page.",
  "listings": [
    {
      "external_ref": "propertyhub-5790593",
      "listing_type": "sale",
      "property_type": "condo",
      "price_thb": 13000000,
      "bedrooms": 2,
      "bathrooms": 2,
      "area_sqm": 62.55,
      "floor_label": "14",
      "building_label": null,
      "project_slug": "ideo-q-sukhumvit-36",
      "developer_slug": "ananda-development",
      "city_slug": "bangkok",
      "district_slug": "khlong-toei",
      "transit_tags": [
        "bts"
      ],
      "title": {
        "en": "2-BR 63 Sqm On 14th Floor, Ideo Q Sukhumvit 36 Near BTS Thong Lor (ID 2618162)",
        "zh": "2-BR 63 Sqm On 14th Floor, Ideo Q Sukhumvit 36 Near BTS Thong Lor (ID 2618162)",
        "th": "2-BR 63 Sqm On 14th Floor, Ideo Q Sukhumvit 36 Near BTS Thong Lor (ID 2618162)"
      },
      "summary": {
        "en": "Sale: 2BR, 62.55 sq.m., 13,000,000 THB. Source PropertyHub #5790593.",
        "zh": "出售：2卧，62.55㎡，13,000,000 泰铢。来源 PropertyHub #5790593。",
        "th": "ขาย: 2 นอน 62.55 ตร.ม. ราคา 13,000,000 บาท (PropertyHub #5790593)"
      },
      "description": {
        "en": "Normalized from PropertyHub listing 5790593. Specs and price from detail __NEXT_DATA__. Availability subject to source page.",
        "zh": "来自 PropertyHub 挂牌 5790593。规格与价格取自详情页 JSON；是否可售/可租以来源页为准。",
        "th": "แปลงจากประกาศ PropertyHub 5790593 สเปกและราคาจากหน้าต้นทาง สถานะให้ยึดแหล่งต้นทาง"
      },
      "featured": false,
      "source": "propertyhub",
      "listing_url": "https://propertyhub.in.th/en/listings/2-br-condo-at-ideo-q-sukhumvit-36-near-bts-thong-lor-id-2618162--ad500923---5790593",
      "source_updated_at": "2026-07-14",
      "collected_at": "2026-07-14",
      "source_captured_at": "2026-07-14",
      "verification_status": "verified",
      "publish_ready": true,
      "latitude": 13.720856043232146,
      "longitude": 100.57638583682271,
      "duplicate_fingerprint": "6c54ee3ca62bfefdc184b46ff9cdabf54036c9b83dfbd2963877b9ade56524a2",
      "source_listing_id": "5790593",
      "normalized_source_url": "https://propertyhub.in.th/en/listings/5790593",
      "source_url_hash": "9e05d2e64c3cf8dc18362fd6b36535bccdfaf823d5c16992f3e1349225c5ea8d",
      "soft_match_fingerprint": "ba99e4611b156b40eaf7a58c0fdf2bc091011c6aac2783b2d1fabc2bc7011573",
      "listing_lifecycle_status": "active",
      "last_seen_at": "2026-07-14",
      "last_verified_at": "2026-07-14"
    },
    {
      "external_ref": "propertyhub-5843945",
      "listing_type": "sale",
      "property_type": "condo",
      "price_thb": 10200000,
      "bedrooms": 2,
      "bathrooms": 1,
      "area_sqm": 53.99,
      "floor_label": "34",
      "building_label": null,
      "project_slug": "ideo-q-sukhumvit-36",
      "developer_slug": "ananda-development",
      "city_slug": "bangkok",
      "district_slug": "khlong-toei",
      "transit_tags": [
        "bts"
      ],
      "title": {
        "en": "2-BR Condo At Ideo Q Sukhumvit 36, 34th-Floor, 400m to BTS Thong Lor (ID 2676907)",
        "zh": "2-BR Condo At Ideo Q Sukhumvit 36, 34th-Floor, 400m to BTS Thong Lor (ID 2676907)",
        "th": "2-BR Condo At Ideo Q Sukhumvit 36, 34th-Floor, 400m to BTS Thong Lor (ID 2676907)"
      },
      "summary": {
        "en": "Sale: 2BR, 53.99 sq.m., 10,200,000 THB. Source PropertyHub #5843945.",
        "zh": "出售：2卧，53.99㎡，10,200,000 泰铢。来源 PropertyHub #5843945。",
        "th": "ขาย: 2 นอน 53.99 ตร.ม. ราคา 10,200,000 บาท (PropertyHub #5843945)"
      },
      "description": {
        "en": "Normalized from PropertyHub listing 5843945. Specs and price from detail __NEXT_DATA__. Availability subject to source page.",
        "zh": "来自 PropertyHub 挂牌 5843945。规格与价格取自详情页 JSON；是否可售/可租以来源页为准。",
        "th": "แปลงจากประกาศ PropertyHub 5843945 สเปกและราคาจากหน้าต้นทาง สถานะให้ยึดแหล่งต้นทาง"
      },
      "featured": false,
      "source": "propertyhub",
      "listing_url": "https://propertyhub.in.th/en/listings/2-br-condo-at-ideo-q-sukhumvit-36-near-bts-thong-lor-id-2676907--bb960a1b---5843945",
      "source_updated_at": "2026-07-14",
      "collected_at": "2026-07-14",
      "source_captured_at": "2026-07-14",
      "verification_status": "verified",
      "publish_ready": true,
      "latitude": 13.720856043232146,
      "longitude": 100.57638583682271,
      "duplicate_fingerprint": "9916504d8b03b66aa721e03e13a698088f4fcaae2d540c833f8d838c7cc8a0c0",
      "source_listing_id": "5843945",
      "normalized_source_url": "https://propertyhub.in.th/en/listings/5843945",
      "source_url_hash": "08d24c740521e9203f42f1416c8a048bc38145f20de8298c37aa170b78fce590",
      "soft_match_fingerprint": "d3fa7597320252cb5034e73238940bcd735ff6356b31b23fc812366d7951cf3c",
      "listing_lifecycle_status": "active",
      "last_seen_at": "2026-07-14",
      "last_verified_at": "2026-07-14"
    },
    {
      "external_ref": "propertyhub-6012040",
      "listing_type": "sale",
      "property_type": "condo",
      "price_thb": 17670000,
      "bedrooms": 2,
      "bathrooms": 2,
      "area_sqm": 63,
      "floor_label": "44",
      "building_label": null,
      "project_slug": "ideo-q-sukhumvit-36",
      "developer_slug": "ananda-development",
      "city_slug": "bangkok",
      "district_slug": "khlong-toei",
      "transit_tags": [
        "bts"
      ],
      "title": {
        "en": "High-Floor 2-BR 63 Sqm Ideo Q Sukhumvit 36, 400m to BTS Thong Lor (ID 2832958)",
        "zh": "High-Floor 2-BR 63 Sqm Ideo Q Sukhumvit 36, 400m to BTS Thong Lor (ID 2832958)",
        "th": "High-Floor 2-BR 63 Sqm Ideo Q Sukhumvit 36, 400m to BTS Thong Lor (ID 2832958)"
      },
      "summary": {
        "en": "Sale: 2BR, 63 sq.m., 17,670,000 THB. Source PropertyHub #6012040.",
        "zh": "出售：2卧，63㎡，17,670,000 泰铢。来源 PropertyHub #6012040。",
        "th": "ขาย: 2 นอน 63 ตร.ม. ราคา 17,670,000 บาท (PropertyHub #6012040)"
      },
      "description": {
        "en": "Normalized from PropertyHub listing 6012040. Specs and price from detail __NEXT_DATA__. Availability subject to source page.",
        "zh": "来自 PropertyHub 挂牌 6012040。规格与价格取自详情页 JSON；是否可售/可租以来源页为准。",
        "th": "แปลงจากประกาศ PropertyHub 6012040 สเปกและราคาจากหน้าต้นทาง สถานะให้ยึดแหล่งต้นทาง"
      },
      "featured": false,
      "source": "propertyhub",
      "listing_url": "https://propertyhub.in.th/en/listings/2-br-condo-at-ideo-q-sukhumvit-36-near-bts-thong-lor-id-2832958--abeb0982---6012040",
      "source_updated_at": "2026-07-14",
      "collected_at": "2026-07-14",
      "source_captured_at": "2026-07-14",
      "verification_status": "verified",
      "publish_ready": true,
      "latitude": 13.720856043232146,
      "longitude": 100.57638583682271,
      "duplicate_fingerprint": "284b6d4d0aec959883785f1882133e014641b8c3aba1fb05006b75cc1513f72d",
      "source_listing_id": "6012040",
      "normalized_source_url": "https://propertyhub.in.th/en/listings/6012040",
      "source_url_hash": "d4e065c013107dbfafd67b2a41824ff882e392d041eab7c4e1a31ff4547b6a90",
      "soft_match_fingerprint": "bf6362327d6621f7e5e6269f1d9923306c103dec0e39c0fd241c3d48e982f462",
      "listing_lifecycle_status": "active",
      "last_seen_at": "2026-07-14",
      "last_verified_at": "2026-07-14"
    },
    {
      "external_ref": "propertyhub-6036423",
      "listing_type": "sale",
      "property_type": "condo",
      "price_thb": 7990000,
      "bedrooms": 1,
      "bathrooms": 1,
      "area_sqm": 45,
      "floor_label": "10",
      "building_label": null,
      "project_slug": "ideo-q-sukhumvit-36",
      "developer_slug": "ananda-development",
      "city_slug": "bangkok",
      "district_slug": "khlong-toei",
      "transit_tags": [
        "bts"
      ],
      "title": {
        "en": "1-BR 45 Sqm Condo At Ideo Q Sukhumvit 36, 400m To BTS Thong Lor (ID 2873702)",
        "zh": "1-BR 45 Sqm Condo At Ideo Q Sukhumvit 36, 400m To BTS Thong Lor (ID 2873702)",
        "th": "1-BR 45 Sqm Condo At Ideo Q Sukhumvit 36, 400m To BTS Thong Lor (ID 2873702)"
      },
      "summary": {
        "en": "Sale: 1BR, 45 sq.m., 7,990,000 THB. Source PropertyHub #6036423.",
        "zh": "出售：1卧，45㎡，7,990,000 泰铢。来源 PropertyHub #6036423。",
        "th": "ขาย: 1 นอน 45 ตร.ม. ราคา 7,990,000 บาท (PropertyHub #6036423)"
      },
      "description": {
        "en": "Normalized from PropertyHub listing 6036423. Specs and price from detail __NEXT_DATA__. Availability subject to source page.",
        "zh": "来自 PropertyHub 挂牌 6036423。规格与价格取自详情页 JSON；是否可售/可租以来源页为准。",
        "th": "แปลงจากประกาศ PropertyHub 6036423 สเปกและราคาจากหน้าต้นทาง สถานะให้ยึดแหล่งต้นทาง"
      },
      "featured": false,
      "source": "propertyhub",
      "listing_url": "https://propertyhub.in.th/en/listings/1-br-condo-at-ideo-q-sukhumvit-36-near-bts-thong-lor-id-2873702--aaed09b7---6036423",
      "source_updated_at": "2026-07-14",
      "collected_at": "2026-07-14",
      "source_captured_at": "2026-07-14",
      "verification_status": "verified",
      "publish_ready": true,
      "latitude": 13.720856043232146,
      "longitude": 100.57638583682271,
      "duplicate_fingerprint": "eb0fbd14c113745afa36204ba4a36a7bb18e149d0c396e968c4240c960c344bf",
      "source_listing_id": "6036423",
      "normalized_source_url": "https://propertyhub.in.th/en/listings/6036423",
      "source_url_hash": "14197da6671e4d250d6c14b6266cf8284a0020f3018f7056b3cc4ddcdacd852b",
      "soft_match_fingerprint": "0a436d6079178c7abe62969be371398af1ded3c45741251558c6c145c15e1e41",
      "listing_lifecycle_status": "active",
      "last_seen_at": "2026-07-14",
      "last_verified_at": "2026-07-14"
    },
    {
      "external_ref": "propertyhub-6065424",
      "listing_type": "sale",
      "property_type": "condo",
      "price_thb": 8190000,
      "bedrooms": 1,
      "bathrooms": 1,
      "area_sqm": 45,
      "floor_label": "",
      "building_label": null,
      "project_slug": "ideo-q-sukhumvit-36",
      "developer_slug": "ananda-development",
      "city_slug": "bangkok",
      "district_slug": "khlong-toei",
      "transit_tags": [
        "bts"
      ],
      "title": {
        "en": "1-BR Condo Ideo Q Sukhumvit 36 Near BTS Thong Lor (400m) (ID 2893821)",
        "zh": "1-BR Condo Ideo Q Sukhumvit 36 Near BTS Thong Lor (400m) (ID 2893821)",
        "th": "1-BR Condo Ideo Q Sukhumvit 36 Near BTS Thong Lor (400m) (ID 2893821)"
      },
      "summary": {
        "en": "Sale: 1BR, 45 sq.m., 8,190,000 THB. Source PropertyHub #6065424.",
        "zh": "出售：1卧，45㎡，8,190,000 泰铢。来源 PropertyHub #6065424。",
        "th": "ขาย: 1 นอน 45 ตร.ม. ราคา 8,190,000 บาท (PropertyHub #6065424)"
      },
      "description": {
        "en": "Normalized from PropertyHub listing 6065424. Specs and price from detail __NEXT_DATA__. Availability subject to source page.",
        "zh": "来自 PropertyHub 挂牌 6065424。规格与价格取自详情页 JSON；是否可售/可租以来源页为准。",
        "th": "แปลงจากประกาศ PropertyHub 6065424 สเปกและราคาจากหน้าต้นทาง สถานะให้ยึดแหล่งต้นทาง"
      },
      "featured": false,
      "source": "propertyhub",
      "listing_url": "https://propertyhub.in.th/en/listings/1-br-condo-at-ideo-q-sukhumvit-36-near-bts-thong-lor-id-2893821--a2eb08ee---6065424",
      "source_updated_at": "2026-07-14",
      "collected_at": "2026-07-14",
      "source_captured_at": "2026-07-14",
      "verification_status": "verified",
      "publish_ready": true,
      "latitude": 13.720856043232146,
      "longitude": 100.57638583682271,
      "duplicate_fingerprint": "2106b5fe3acdd21829cdd8d6afcc64d0b7ab1d51130dab887ea4597902b2fcab",
      "source_listing_id": "6065424",
      "normalized_source_url": "https://propertyhub.in.th/en/listings/6065424",
      "source_url_hash": "f2b983784564ae3a50dbc2b47e304d46030ea284758ae07e7f28cf5d66e83e1e",
      "soft_match_fingerprint": "a5a86d01c8d4fb3a7dc6991e01b6e0b727283c351b3b54a2ef0d972543404938",
      "listing_lifecycle_status": "active",
      "last_seen_at": "2026-07-14",
      "last_verified_at": "2026-07-14"
    },
    {
      "external_ref": "propertyhub-6158799",
      "listing_type": "sale",
      "property_type": "condo",
      "price_thb": 8400000,
      "bedrooms": 1,
      "bathrooms": 1,
      "area_sqm": 45,
      "floor_label": "34",
      "building_label": null,
      "project_slug": "ideo-q-sukhumvit-36",
      "developer_slug": "ananda-development",
      "city_slug": "bangkok",
      "district_slug": "khlong-toei",
      "transit_tags": [
        "bts"
      ],
      "title": {
        "en": "1-BR 45 Sqm On 34th Floor At Ideo Q Sukhumvit 36, 400m to BTS Thong Lor (ID 3013452)",
        "zh": "1-BR 45 Sqm On 34th Floor At Ideo Q Sukhumvit 36, 400m to BTS Thong Lor (ID 3013452)",
        "th": "1-BR 45 Sqm On 34th Floor At Ideo Q Sukhumvit 36, 400m to BTS Thong Lor (ID 3013452)"
      },
      "summary": {
        "en": "Sale: 1BR, 45 sq.m., 8,400,000 THB. Source PropertyHub #6158799.",
        "zh": "出售：1卧，45㎡，8,400,000 泰铢。来源 PropertyHub #6158799。",
        "th": "ขาย: 1 นอน 45 ตร.ม. ราคา 8,400,000 บาท (PropertyHub #6158799)"
      },
      "description": {
        "en": "Normalized from PropertyHub listing 6158799. Specs and price from detail __NEXT_DATA__. Availability subject to source page.",
        "zh": "来自 PropertyHub 挂牌 6158799。规格与价格取自详情页 JSON；是否可售/可租以来源页为准。",
        "th": "แปลงจากประกาศ PropertyHub 6158799 สเปกและราคาจากหน้าต้นทาง สถานะให้ยึดแหล่งต้นทาง"
      },
      "featured": false,
      "source": "propertyhub",
      "listing_url": "https://propertyhub.in.th/en/listings/1-br-condo-at-ideo-q-sukhumvit-36-near-bts-thong-lor-id-3013452---6158799",
      "source_updated_at": "2026-07-14",
      "collected_at": "2026-07-14",
      "source_captured_at": "2026-07-14",
      "verification_status": "verified",
      "publish_ready": true,
      "latitude": 13.720856043232146,
      "longitude": 100.57638583682271,
      "duplicate_fingerprint": "5962a4e562622b855a218943a85173fae202839c0514844cae858a1448e5e23d",
      "source_listing_id": "6158799",
      "normalized_source_url": "https://propertyhub.in.th/en/listings/6158799",
      "source_url_hash": "7a60ede6cf792f747b3fda95acaa1d6602baf557bcaeea2a8d577e2565598950",
      "soft_match_fingerprint": "f85b9952be161c6eebe6ab801ba52d573a1bcb3e31337d4c70668686606ab311",
      "listing_lifecycle_status": "active",
      "last_seen_at": "2026-07-14",
      "last_verified_at": "2026-07-14"
    },
    {
      "external_ref": "propertyhub-6174837",
      "listing_type": "sale",
      "property_type": "condo",
      "price_thb": 13500000,
      "bedrooms": 2,
      "bathrooms": 2,
      "area_sqm": 65,
      "floor_label": "20-25",
      "building_label": null,
      "project_slug": "ideo-q-sukhumvit-36",
      "developer_slug": "ananda-development",
      "city_slug": "bangkok",
      "district_slug": "khlong-toei",
      "transit_tags": [
        "bts"
      ],
      "title": {
        "en": "2-BR 65 Sqm High-Floor For Sale, Ideo Q Sukhumvit 36, BTS Thong Lor 400m (ID 3034291)",
        "zh": "2-BR 65 Sqm High-Floor For Sale, Ideo Q Sukhumvit 36, BTS Thong Lor 400m (ID 3034291)",
        "th": "2-BR 65 Sqm High-Floor For Sale, Ideo Q Sukhumvit 36, BTS Thong Lor 400m (ID 3034291)"
      },
      "summary": {
        "en": "Sale: 2BR, 65 sq.m., 13,500,000 THB. Source PropertyHub #6174837.",
        "zh": "出售：2卧，65㎡，13,500,000 泰铢。来源 PropertyHub #6174837。",
        "th": "ขาย: 2 นอน 65 ตร.ม. ราคา 13,500,000 บาท (PropertyHub #6174837)"
      },
      "description": {
        "en": "Normalized from PropertyHub listing 6174837. Specs and price from detail __NEXT_DATA__. Availability subject to source page.",
        "zh": "来自 PropertyHub 挂牌 6174837。规格与价格取自详情页 JSON；是否可售/可租以来源页为准。",
        "th": "แปลงจากประกาศ PropertyHub 6174837 สเปกและราคาจากหน้าต้นทาง สถานะให้ยึดแหล่งต้นทาง"
      },
      "featured": false,
      "source": "propertyhub",
      "listing_url": "https://propertyhub.in.th/en/listings/2-br-condo-at-ideo-q-sukhumvit-36-near-bts-thong-lor-id-3034291---6174837",
      "source_updated_at": "2026-07-14",
      "collected_at": "2026-07-14",
      "source_captured_at": "2026-07-14",
      "verification_status": "verified",
      "publish_ready": true,
      "latitude": 13.720856043232146,
      "longitude": 100.57638583682271,
      "duplicate_fingerprint": "18b5f24d1d7990fdc1780fa09586904bb2dfaf80ab4262b748900a05921ddfcb",
      "source_listing_id": "6174837",
      "normalized_source_url": "https://propertyhub.in.th/en/listings/6174837",
      "source_url_hash": "c6f245f77d2362f0a6b27ef9af7e5a880c58e3c16b811ffcc3446c3a705de73d",
      "soft_match_fingerprint": "a312d30ddff6a1c8c38327e2bed7773ecb709175e70ffe6a3f388ca80dd07fae",
      "listing_lifecycle_status": "active",
      "last_seen_at": "2026-07-14",
      "last_verified_at": "2026-07-14"
    },
    {
      "external_ref": "propertyhub-5020827",
      "listing_type": "sale",
      "property_type": "condo",
      "price_thb": 9900000,
      "bedrooms": 1,
      "bathrooms": 1,
      "area_sqm": 51,
      "floor_label": "26A",
      "building_label": null,
      "project_slug": "ideo-q-sukhumvit-36",
      "developer_slug": "ananda-development",
      "city_slug": "bangkok",
      "district_slug": "khlong-toei",
      "transit_tags": [
        "bts"
      ],
      "title": {
        "en": "1-BR Condo At Ideo Q Sukhumvit 36, 400m To BTS Thong Lor (ID 2073859)",
        "zh": "1-BR Condo At Ideo Q Sukhumvit 36, 400m To BTS Thong Lor (ID 2073859)",
        "th": "1-BR Condo At Ideo Q Sukhumvit 36, 400m To BTS Thong Lor (ID 2073859)"
      },
      "summary": {
        "en": "Sale: 1BR, 51 sq.m., 9,900,000 THB. Source PropertyHub #5020827.",
        "zh": "出售：1卧，51㎡，9,900,000 泰铢。来源 PropertyHub #5020827。",
        "th": "ขาย: 1 นอน 51 ตร.ม. ราคา 9,900,000 บาท (PropertyHub #5020827)"
      },
      "description": {
        "en": "Normalized from PropertyHub listing 5020827. Specs and price from detail __NEXT_DATA__. Availability subject to source page.",
        "zh": "来自 PropertyHub 挂牌 5020827。规格与价格取自详情页 JSON；是否可售/可租以来源页为准。",
        "th": "แปลงจากประกาศ PropertyHub 5020827 สเปกและราคาจากหน้าต้นทาง สถานะให้ยึดแหล่งต้นทาง"
      },
      "featured": false,
      "source": "propertyhub",
      "listing_url": "https://propertyhub.in.th/en/listings/1-br-condo-at-ideo-q-sukhumvit-36-near-bts-thong-lor-id-2073859---5020827",
      "source_updated_at": "2026-07-14",
      "collected_at": "2026-07-14",
      "source_captured_at": "2026-07-14",
      "verification_status": "verified",
      "publish_ready": true,
      "latitude": 13.720856043232146,
      "longitude": 100.57638583682271,
      "duplicate_fingerprint": "927a689b8dad86f62db30650c476af5afd3b1936529303d5ee29c530e6c6cef7",
      "source_listing_id": "5020827",
      "normalized_source_url": "https://propertyhub.in.th/en/listings/5020827",
      "source_url_hash": "1b0c9c9bf61c1d952581e0b0cfdaeaa82dfc7daae60b432bd8edcda47347bd49",
      "soft_match_fingerprint": "68d5a7de1cb38c1a4825b193bb13ab0a2f20611d4e0e3a102707110a37193900",
      "listing_lifecycle_status": "active",
      "last_seen_at": "2026-07-14",
      "last_verified_at": "2026-07-14"
    },
    {
      "external_ref": "propertyhub-6036435",
      "listing_type": "sale",
      "property_type": "condo",
      "price_thb": 10200000,
      "bedrooms": 1,
      "bathrooms": 1,
      "area_sqm": 44.78,
      "floor_label": "25",
      "building_label": null,
      "project_slug": "ideo-q-sukhumvit-36",
      "developer_slug": "ananda-development",
      "city_slug": "bangkok",
      "district_slug": "khlong-toei",
      "transit_tags": [
        "bts"
      ],
      "title": {
        "en": "High-Floor 1-BR 45 Sqm At Ideo Q Sukhumvit 36, 400m to BTS Thong Lor (ID 2873889)",
        "zh": "High-Floor 1-BR 45 Sqm At Ideo Q Sukhumvit 36, 400m to BTS Thong Lor (ID 2873889)",
        "th": "High-Floor 1-BR 45 Sqm At Ideo Q Sukhumvit 36, 400m to BTS Thong Lor (ID 2873889)"
      },
      "summary": {
        "en": "Sale: 1BR, 44.78 sq.m., 10,200,000 THB. Source PropertyHub #6036435.",
        "zh": "出售：1卧，44.78㎡，10,200,000 泰铢。来源 PropertyHub #6036435。",
        "th": "ขาย: 1 นอน 44.78 ตร.ม. ราคา 10,200,000 บาท (PropertyHub #6036435)"
      },
      "description": {
        "en": "Normalized from PropertyHub listing 6036435. Specs and price from detail __NEXT_DATA__. Availability subject to source page.",
        "zh": "来自 PropertyHub 挂牌 6036435。规格与价格取自详情页 JSON；是否可售/可租以来源页为准。",
        "th": "แปลงจากประกาศ PropertyHub 6036435 สเปกและราคาจากหน้าต้นทาง สถานะให้ยึดแหล่งต้นทาง"
      },
      "featured": false,
      "source": "propertyhub",
      "listing_url": "https://propertyhub.in.th/en/listings/1-br-condo-at-ideo-q-sukhumvit-36-near-bts-thong-lor-id-2873889--a846097e---6036435",
      "source_updated_at": "2026-07-14",
      "collected_at": "2026-07-14",
      "source_captured_at": "2026-07-14",
      "verification_status": "verified",
      "publish_ready": true,
      "latitude": 13.720856043232146,
      "longitude": 100.57638583682271,
      "duplicate_fingerprint": "8e6feef49f8b69bee2f71896c211245ea61e11991662e08669ad6f344574e07e",
      "source_listing_id": "6036435",
      "normalized_source_url": "https://propertyhub.in.th/en/listings/6036435",
      "source_url_hash": "8c243e43d0d79cd39db0239bc30fe5b69747a78f927f15a5f6a66c1273c3f410",
      "soft_match_fingerprint": "5b3a9881f83072013ec9e774d28f316ce57e42bff9ddf01e801c58f8b1b79b44",
      "listing_lifecycle_status": "active",
      "last_seen_at": "2026-07-14",
      "last_verified_at": "2026-07-14"
    },
    {
      "external_ref": "propertyhub-6136497",
      "listing_type": "sale",
      "property_type": "condo",
      "price_thb": 13290000,
      "bedrooms": 2,
      "bathrooms": 2,
      "area_sqm": 64,
      "floor_label": "20",
      "building_label": null,
      "project_slug": "ideo-q-sukhumvit-36",
      "developer_slug": "ananda-development",
      "city_slug": "bangkok",
      "district_slug": "khlong-toei",
      "transit_tags": [
        "bts"
      ],
      "title": {
        "en": "High-Floor 2-BR 64 Sqm At Ideo Q Sukhumvit 36, 400m to BTS Thong Lor (ID 2657971)",
        "zh": "High-Floor 2-BR 64 Sqm At Ideo Q Sukhumvit 36, 400m to BTS Thong Lor (ID 2657971)",
        "th": "High-Floor 2-BR 64 Sqm At Ideo Q Sukhumvit 36, 400m to BTS Thong Lor (ID 2657971)"
      },
      "summary": {
        "en": "Sale: 2BR, 64 sq.m., 13,290,000 THB. Source PropertyHub #6136497.",
        "zh": "出售：2卧，64㎡，13,290,000 泰铢。来源 PropertyHub #6136497。",
        "th": "ขาย: 2 นอน 64 ตร.ม. ราคา 13,290,000 บาท (PropertyHub #6136497)"
      },
      "description": {
        "en": "Normalized from PropertyHub listing 6136497. Specs and price from detail __NEXT_DATA__. Availability subject to source page.",
        "zh": "来自 PropertyHub 挂牌 6136497。规格与价格取自详情页 JSON；是否可售/可租以来源页为准。",
        "th": "แปลงจากประกาศ PropertyHub 6136497 สเปกและราคาจากหน้าต้นทาง สถานะให้ยึดแหล่งต้นทาง"
      },
      "featured": false,
      "source": "propertyhub",
      "listing_url": "https://propertyhub.in.th/en/listings/2-br-condo-at-ideo-q-sukhumvit-36-near-bts-thong-lor-id-2657971--bd830a08---6136497",
      "source_updated_at": "2026-07-14",
      "collected_at": "2026-07-14",
      "source_captured_at": "2026-07-14",
      "verification_status": "verified",
      "publish_ready": true,
      "latitude": 13.720856043232146,
      "longitude": 100.57638583682271,
      "duplicate_fingerprint": "1e4b4dd9eb7219dc89348a3cee9447ac9dd0bbc62345465f5e982e2c348f8fe3",
      "source_listing_id": "6136497",
      "normalized_source_url": "https://propertyhub.in.th/en/listings/6136497",
      "source_url_hash": "1a15d26eab44e2a7b75ad764249f6a6bf2bfed96f425b5fe66c357c53e7bf9db",
      "soft_match_fingerprint": "b45507595783b578ecc4c6e7caf8eb87df23e143e9237bc096fdc902f848db07",
      "listing_lifecycle_status": "active",
      "last_seen_at": "2026-07-14",
      "last_verified_at": "2026-07-14"
    },
    {
      "external_ref": "propertyhub-5775839",
      "listing_type": "rent",
      "property_type": "condo",
      "price_thb": 55000,
      "bedrooms": 2,
      "bathrooms": 2,
      "area_sqm": 65.5,
      "floor_label": "26",
      "building_label": null,
      "project_slug": "ideo-q-sukhumvit-36",
      "developer_slug": "ananda-development",
      "city_slug": "bangkok",
      "district_slug": "khlong-toei",
      "transit_tags": [
        "bts"
      ],
      "title": {
        "en": "2-BR 65 Sqm, High-Floor At Ideo Q Sukhumvit 36 Near BTS Thong Lor (ID 2612266)",
        "zh": "2-BR 65 Sqm, High-Floor At Ideo Q Sukhumvit 36 Near BTS Thong Lor (ID 2612266)",
        "th": "2-BR 65 Sqm, High-Floor At Ideo Q Sukhumvit 36 Near BTS Thong Lor (ID 2612266)"
      },
      "summary": {
        "en": "Rent: 2BR, 65.5 sq.m., 55,000 THB. Source PropertyHub #5775839.",
        "zh": "出租：2卧，65.5㎡，55,000 泰铢。来源 PropertyHub #5775839。",
        "th": "เช่า: 2 นอน 65.5 ตร.ม. ราคา 55,000 บาท (PropertyHub #5775839)"
      },
      "description": {
        "en": "Normalized from PropertyHub listing 5775839. Specs and price from detail __NEXT_DATA__. Availability subject to source page.",
        "zh": "来自 PropertyHub 挂牌 5775839。规格与价格取自详情页 JSON；是否可售/可租以来源页为准。",
        "th": "แปลงจากประกาศ PropertyHub 5775839 สเปกและราคาจากหน้าต้นทาง สถานะให้ยึดแหล่งต้นทาง"
      },
      "featured": false,
      "source": "propertyhub",
      "listing_url": "https://propertyhub.in.th/en/listings/2-br-condo-at-ideo-q-sukhumvit-36-near-bts-thong-lor-id-2612266--9fa408ee---5775839",
      "source_updated_at": "2026-07-14",
      "collected_at": "2026-07-14",
      "source_captured_at": "2026-07-14",
      "verification_status": "verified",
      "publish_ready": true,
      "latitude": 13.720856043232146,
      "longitude": 100.57638583682271,
      "duplicate_fingerprint": "c8e3343b56b0199207d86d68fc327c5461915e118ec9fc0040ca632da636051c",
      "source_listing_id": "5775839",
      "normalized_source_url": "https://propertyhub.in.th/en/listings/5775839",
      "source_url_hash": "3fc28f8397af7be4a9f60b9a11e09edfa445c913b5e5c9238ab5b8a771cd0a10",
      "soft_match_fingerprint": "5a7ffd5569e3ee5073a7014c20adffcd2ae36a99592b52116867bfc621469ff0",
      "listing_lifecycle_status": "active",
      "last_seen_at": "2026-07-14",
      "last_verified_at": "2026-07-14"
    },
    {
      "external_ref": "propertyhub-6210525",
      "listing_type": "rent",
      "property_type": "condo",
      "price_thb": 40000,
      "bedrooms": 1,
      "bathrooms": 1,
      "area_sqm": 45,
      "floor_label": "18A",
      "building_label": null,
      "project_slug": "ideo-q-sukhumvit-36",
      "developer_slug": "ananda-development",
      "city_slug": "bangkok",
      "district_slug": "khlong-toei",
      "transit_tags": [
        "bts"
      ],
      "title": {
        "en": "1-BR 45 Sqm, 18A Floor, Ideo Q Sukhumvit 36, 400m to BTS Thong Lor (ID 2366498)",
        "zh": "1-BR 45 Sqm, 18A Floor, Ideo Q Sukhumvit 36, 400m to BTS Thong Lor (ID 2366498)",
        "th": "1-BR 45 Sqm, 18A Floor, Ideo Q Sukhumvit 36, 400m to BTS Thong Lor (ID 2366498)"
      },
      "summary": {
        "en": "Rent: 1BR, 45 sq.m., 40,000 THB. Source PropertyHub #6210525.",
        "zh": "出租：1卧，45㎡，40,000 泰铢。来源 PropertyHub #6210525。",
        "th": "เช่า: 1 นอน 45 ตร.ม. ราคา 40,000 บาท (PropertyHub #6210525)"
      },
      "description": {
        "en": "Normalized from PropertyHub listing 6210525. Specs and price from detail __NEXT_DATA__. Availability subject to source page.",
        "zh": "来自 PropertyHub 挂牌 6210525。规格与价格取自详情页 JSON；是否可售/可租以来源页为准。",
        "th": "แปลงจากประกาศ PropertyHub 6210525 สเปกและราคาจากหน้าต้นทาง สถานะให้ยึดแหล่งต้นทาง"
      },
      "featured": false,
      "source": "propertyhub",
      "listing_url": "https://propertyhub.in.th/en/listings/1-br-45-sqm-18a-floor-ideo-q-sukhumvit-36-400m-to-bts-thong-lor-id-2366498---6210525",
      "source_updated_at": "2026-07-14",
      "collected_at": "2026-07-14",
      "source_captured_at": "2026-07-14",
      "verification_status": "verified",
      "publish_ready": true,
      "latitude": 13.720856043232146,
      "longitude": 100.57638583682271,
      "duplicate_fingerprint": "6770834275b5392d79a0d87228ff0879885e2687b970fa441235cefd506e850c",
      "source_listing_id": "6210525",
      "normalized_source_url": "https://propertyhub.in.th/en/listings/6210525",
      "source_url_hash": "cd0b3b4f888c20de151402a574c247eaa8760983c273a1d6746a8f875e88d4bc",
      "soft_match_fingerprint": "d8d9e3d41b44da30cc46fafe98fa1046664d327225d7be5d9f91a912529c12d3",
      "listing_lifecycle_status": "active",
      "last_seen_at": "2026-07-14",
      "last_verified_at": "2026-07-14"
    },
    {
      "external_ref": "propertyhub-6152203",
      "listing_type": "rent",
      "property_type": "condo",
      "price_thb": 60000,
      "bedrooms": 2,
      "bathrooms": 2,
      "area_sqm": 71,
      "floor_label": "32",
      "building_label": null,
      "project_slug": "ideo-q-sukhumvit-36",
      "developer_slug": "ananda-development",
      "city_slug": "bangkok",
      "district_slug": "khlong-toei",
      "transit_tags": [
        "bts"
      ],
      "title": {
        "en": "32nd-Floor 2-BR 71 Sqm Condo At Ideo Q Sukhumvit 36 Near BTS Thong Lor (ID 3001138)",
        "zh": "32nd-Floor 2-BR 71 Sqm Condo At Ideo Q Sukhumvit 36 Near BTS Thong Lor (ID 3001138)",
        "th": "32nd-Floor 2-BR 71 Sqm Condo At Ideo Q Sukhumvit 36 Near BTS Thong Lor (ID 3001138)"
      },
      "summary": {
        "en": "Rent: 2BR, 71 sq.m., 60,000 THB. Source PropertyHub #6152203.",
        "zh": "出租：2卧，71㎡，60,000 泰铢。来源 PropertyHub #6152203。",
        "th": "เช่า: 2 นอน 71 ตร.ม. ราคา 60,000 บาท (PropertyHub #6152203)"
      },
      "description": {
        "en": "Normalized from PropertyHub listing 6152203. Specs and price from detail __NEXT_DATA__. Availability subject to source page.",
        "zh": "来自 PropertyHub 挂牌 6152203。规格与价格取自详情页 JSON；是否可售/可租以来源页为准。",
        "th": "แปลงจากประกาศ PropertyHub 6152203 สเปกและราคาจากหน้าต้นทาง สถานะให้ยึดแหล่งต้นทาง"
      },
      "featured": false,
      "source": "propertyhub",
      "listing_url": "https://propertyhub.in.th/en/listings/2-br-condo-at-ideo-q-sukhumvit-36-near-bts-thong-lor-id-3001138--a46608f2---6152203",
      "source_updated_at": "2026-07-14",
      "collected_at": "2026-07-14",
      "source_captured_at": "2026-07-14",
      "verification_status": "verified",
      "publish_ready": true,
      "latitude": 13.720856043232146,
      "longitude": 100.57638583682271,
      "duplicate_fingerprint": "44c0cd270ea135631f50b0e95305d7f05e247443aeea92b6417f520a0653b5e9",
      "source_listing_id": "6152203",
      "normalized_source_url": "https://propertyhub.in.th/en/listings/6152203",
      "source_url_hash": "997e00081295f7a1b653d8321fba5ec9fa39f07c3a0d56385747e0855062d78d",
      "soft_match_fingerprint": "6495810c1c8feb7b48b47346d4069210772c360dabc4af78b5ed4a68eb35695a",
      "listing_lifecycle_status": "active",
      "last_seen_at": "2026-07-14",
      "last_verified_at": "2026-07-14"
    },
    {
      "external_ref": "propertyhub-4164826",
      "listing_type": "rent",
      "property_type": "condo",
      "price_thb": 40000,
      "bedrooms": 1,
      "bathrooms": 1,
      "area_sqm": 44,
      "floor_label": "8",
      "building_label": null,
      "project_slug": "ideo-q-sukhumvit-36",
      "developer_slug": "ananda-development",
      "city_slug": "bangkok",
      "district_slug": "khlong-toei",
      "transit_tags": [
        "bts"
      ],
      "title": {
        "en": "1-BR 44 Sqm At Ideo Q Sukhumvit 36 Near BTS Thong Lor (400m) (ID 1001395)",
        "zh": "1-BR 44 Sqm At Ideo Q Sukhumvit 36 Near BTS Thong Lor (400m) (ID 1001395)",
        "th": "1-BR 44 Sqm At Ideo Q Sukhumvit 36 Near BTS Thong Lor (400m) (ID 1001395)"
      },
      "summary": {
        "en": "Rent: 1BR, 44 sq.m., 40,000 THB. Source PropertyHub #4164826.",
        "zh": "出租：1卧，44㎡，40,000 泰铢。来源 PropertyHub #4164826。",
        "th": "เช่า: 1 นอน 44 ตร.ม. ราคา 40,000 บาท (PropertyHub #4164826)"
      },
      "description": {
        "en": "Normalized from PropertyHub listing 4164826. Specs and price from detail __NEXT_DATA__. Availability subject to source page.",
        "zh": "来自 PropertyHub 挂牌 4164826。规格与价格取自详情页 JSON；是否可售/可租以来源页为准。",
        "th": "แปลงจากประกาศ PropertyHub 4164826 สเปกและราคาจากหน้าต้นทาง สถานะให้ยึดแหล่งต้นทาง"
      },
      "featured": false,
      "source": "propertyhub",
      "listing_url": "https://propertyhub.in.th/en/listings/1-br-44-sqm-at-ideo-q-sukhumvit-36-near-bts-thong-lor-400m-id-1001395---4164826",
      "source_updated_at": "2026-07-14",
      "collected_at": "2026-07-14",
      "source_captured_at": "2026-07-14",
      "verification_status": "verified",
      "publish_ready": true,
      "latitude": 13.720856043232146,
      "longitude": 100.57638583682271,
      "duplicate_fingerprint": "4ad53839066788114f6a2da51b03201f455dd7603c8452f905cf98a22379273f",
      "source_listing_id": "4164826",
      "normalized_source_url": "https://propertyhub.in.th/en/listings/4164826",
      "source_url_hash": "3911205c3fd83401509d6e87fbca9f2a19ef4425ae189f155df35076281c3b4d",
      "soft_match_fingerprint": "d6ccf4efe10125010395d3cad937682a3e6b3bd722ae6097d4fabf22e50fed80",
      "listing_lifecycle_status": "active",
      "last_seen_at": "2026-07-14",
      "last_verified_at": "2026-07-14"
    },
    {
      "external_ref": "propertyhub-4479051",
      "listing_type": "rent",
      "property_type": "condo",
      "price_thb": 45000,
      "bedrooms": 2,
      "bathrooms": 1,
      "area_sqm": 50,
      "floor_label": "8",
      "building_label": null,
      "project_slug": "ideo-q-sukhumvit-36",
      "developer_slug": "ananda-development",
      "city_slug": "bangkok",
      "district_slug": "khlong-toei",
      "transit_tags": [
        "bts"
      ],
      "title": {
        "en": "2-BR 50 Sqm At Ideo Q Sukhumvit 36, 400m to BTS Thong Lor (ID 1537878)",
        "zh": "2-BR 50 Sqm At Ideo Q Sukhumvit 36, 400m to BTS Thong Lor (ID 1537878)",
        "th": "2-BR 50 Sqm At Ideo Q Sukhumvit 36, 400m to BTS Thong Lor (ID 1537878)"
      },
      "summary": {
        "en": "Rent: 2BR, 50 sq.m., 45,000 THB. Source PropertyHub #4479051.",
        "zh": "出租：2卧，50㎡，45,000 泰铢。来源 PropertyHub #4479051。",
        "th": "เช่า: 2 นอน 50 ตร.ม. ราคา 45,000 บาท (PropertyHub #4479051)"
      },
      "description": {
        "en": "Normalized from PropertyHub listing 4479051. Specs and price from detail __NEXT_DATA__. Availability subject to source page.",
        "zh": "来自 PropertyHub 挂牌 4479051。规格与价格取自详情页 JSON；是否可售/可租以来源页为准。",
        "th": "แปลงจากประกาศ PropertyHub 4479051 สเปกและราคาจากหน้าต้นทาง สถานะให้ยึดแหล่งต้นทาง"
      },
      "featured": false,
      "source": "propertyhub",
      "listing_url": "https://propertyhub.in.th/en/listings/2-br-condo-at-ideo-q-sukhumvit-36-near-bts-thong-lor-id-1537878--aa6508f1---4479051",
      "source_updated_at": "2026-07-14",
      "collected_at": "2026-07-14",
      "source_captured_at": "2026-07-14",
      "verification_status": "verified",
      "publish_ready": true,
      "latitude": 13.720856043232146,
      "longitude": 100.57638583682271,
      "duplicate_fingerprint": "ffd6138e5e9f90fa60e49cd51f19823ca0d755a38db0bdc8c90d9cc671e5e5c8",
      "source_listing_id": "4479051",
      "normalized_source_url": "https://propertyhub.in.th/en/listings/4479051",
      "source_url_hash": "b41cb3785647bbae105fef0ce35cd71f8f3b29c45dc08bbb4aacc09b8c7c5289",
      "soft_match_fingerprint": "13aa3b015303128acffeae99d11f6ac040614decea6db0f9afc37a694da1fcd0",
      "listing_lifecycle_status": "active",
      "last_seen_at": "2026-07-14",
      "last_verified_at": "2026-07-14"
    },
    {
      "external_ref": "propertyhub-5157561",
      "listing_type": "rent",
      "property_type": "condo",
      "price_thb": 39000,
      "bedrooms": 1,
      "bathrooms": 1,
      "area_sqm": 44.78,
      "floor_label": "15",
      "building_label": null,
      "project_slug": "ideo-q-sukhumvit-36",
      "developer_slug": "ananda-development",
      "city_slug": "bangkok",
      "district_slug": "khlong-toei",
      "transit_tags": [
        "bts"
      ],
      "title": {
        "en": "1-BR Condo Ideo Q Sukhumvit 36, 15th-Floor 45 Sqm Near BTS Thong Lor 400m (ID 2136122)",
        "zh": "1-BR Condo Ideo Q Sukhumvit 36, 15th-Floor 45 Sqm Near BTS Thong Lor 400m (ID 2136122)",
        "th": "1-BR Condo Ideo Q Sukhumvit 36, 15th-Floor 45 Sqm Near BTS Thong Lor 400m (ID 2136122)"
      },
      "summary": {
        "en": "Rent: 1BR, 44.78 sq.m., 39,000 THB. Source PropertyHub #5157561.",
        "zh": "出租：1卧，44.78㎡，39,000 泰铢。来源 PropertyHub #5157561。",
        "th": "เช่า: 1 นอน 44.78 ตร.ม. ราคา 39,000 บาท (PropertyHub #5157561)"
      },
      "description": {
        "en": "Normalized from PropertyHub listing 5157561. Specs and price from detail __NEXT_DATA__. Availability subject to source page.",
        "zh": "来自 PropertyHub 挂牌 5157561。规格与价格取自详情页 JSON；是否可售/可租以来源页为准。",
        "th": "แปลงจากประกาศ PropertyHub 5157561 สเปกและราคาจากหน้าต้นทาง สถานะให้ยึดแหล่งต้นทาง"
      },
      "featured": false,
      "source": "propertyhub",
      "listing_url": "https://propertyhub.in.th/en/listings/1-br-condo-at-ideo-q-sukhumvit-36-near-bts-thong-lor-id-2136122---5157561",
      "source_updated_at": "2026-07-14",
      "collected_at": "2026-07-14",
      "source_captured_at": "2026-07-14",
      "verification_status": "verified",
      "publish_ready": true,
      "latitude": 13.720856043232146,
      "longitude": 100.57638583682271,
      "duplicate_fingerprint": "21b93a43cb5638a772e1ee5838796b3cfaf574ffb9d3d70ff42ba8b66c70f55d",
      "source_listing_id": "5157561",
      "normalized_source_url": "https://propertyhub.in.th/en/listings/5157561",
      "source_url_hash": "911edb720bbffe76c95442c32120ca3e282401504074dc247b89bbbd4c161834",
      "soft_match_fingerprint": "5280b5f619b23f16877d10845b1d267002eb204d332590cbc30b1c0a0a504cf6",
      "listing_lifecycle_status": "active",
      "last_seen_at": "2026-07-14",
      "last_verified_at": "2026-07-14"
    },
    {
      "external_ref": "propertyhub-5511022",
      "listing_type": "rent",
      "property_type": "condo",
      "price_thb": 27000,
      "bedrooms": 1,
      "bathrooms": 1,
      "area_sqm": 31,
      "floor_label": "29",
      "building_label": null,
      "project_slug": "ideo-q-sukhumvit-36",
      "developer_slug": "ananda-development",
      "city_slug": "bangkok",
      "district_slug": "khlong-toei",
      "transit_tags": [
        "bts"
      ],
      "title": {
        "en": "Well-Priced 1-BR 31 Sqm On 29th Floor, Ideo Q Sukhumvit 36, 400m to BTS Thong Lor (ID 2363044)",
        "zh": "Well-Priced 1-BR 31 Sqm On 29th Floor, Ideo Q Sukhumvit 36, 400m to BTS Thong Lor (ID 2363044)",
        "th": "Well-Priced 1-BR 31 Sqm On 29th Floor, Ideo Q Sukhumvit 36, 400m to BTS Thong Lor (ID 2363044)"
      },
      "summary": {
        "en": "Rent: 1BR, 31 sq.m., 27,000 THB. Source PropertyHub #5511022.",
        "zh": "出租：1卧，31㎡，27,000 泰铢。来源 PropertyHub #5511022。",
        "th": "เช่า: 1 นอน 31 ตร.ม. ราคา 27,000 บาท (PropertyHub #5511022)"
      },
      "description": {
        "en": "Normalized from PropertyHub listing 5511022. Specs and price from detail __NEXT_DATA__. Availability subject to source page.",
        "zh": "来自 PropertyHub 挂牌 5511022。规格与价格取自详情页 JSON；是否可售/可租以来源页为准。",
        "th": "แปลงจากประกาศ PropertyHub 5511022 สเปกและราคาจากหน้าต้นทาง สถานะให้ยึดแหล่งต้นทาง"
      },
      "featured": false,
      "source": "propertyhub",
      "listing_url": "https://propertyhub.in.th/en/listings/1-br-condo-at-ideo-q-sukhumvit-36-near-bts-thong-lor-id-2363044---5511022",
      "source_updated_at": "2026-07-14",
      "collected_at": "2026-07-14",
      "source_captured_at": "2026-07-14",
      "verification_status": "verified",
      "publish_ready": true,
      "latitude": 13.720856043232146,
      "longitude": 100.57638583682271,
      "duplicate_fingerprint": "1dd448e5da2633c62e358d8236d6a7020dceae7523b992e05ac7218742bbd632",
      "source_listing_id": "5511022",
      "normalized_source_url": "https://propertyhub.in.th/en/listings/5511022",
      "source_url_hash": "35a0c0a5e6577c08bc87761ee04e6cda68541461cac04b987921d5608c79926f",
      "soft_match_fingerprint": "99dfcdad13535e99ba16c724a930b41e0b97459d355553a3341cc3815266b458",
      "listing_lifecycle_status": "active",
      "last_seen_at": "2026-07-14",
      "last_verified_at": "2026-07-14"
    },
    {
      "external_ref": "propertyhub-5761491",
      "listing_type": "rent",
      "property_type": "condo",
      "price_thb": 38000,
      "bedrooms": 1,
      "bathrooms": 1,
      "area_sqm": 44.48,
      "floor_label": "7",
      "building_label": null,
      "project_slug": "ideo-q-sukhumvit-36",
      "developer_slug": "ananda-development",
      "city_slug": "bangkok",
      "district_slug": "khlong-toei",
      "transit_tags": [
        "bts"
      ],
      "title": {
        "en": "1-BR 44 Sqm Condo At Ideo Q Sukhumvit 36, 400m To BTS Thong Lor (ID 2600359)",
        "zh": "1-BR 44 Sqm Condo At Ideo Q Sukhumvit 36, 400m To BTS Thong Lor (ID 2600359)",
        "th": "1-BR 44 Sqm Condo At Ideo Q Sukhumvit 36, 400m To BTS Thong Lor (ID 2600359)"
      },
      "summary": {
        "en": "Rent: 1BR, 44.48 sq.m., 38,000 THB. Source PropertyHub #5761491.",
        "zh": "出租：1卧，44.48㎡，38,000 泰铢。来源 PropertyHub #5761491。",
        "th": "เช่า: 1 นอน 44.48 ตร.ม. ราคา 38,000 บาท (PropertyHub #5761491)"
      },
      "description": {
        "en": "Normalized from PropertyHub listing 5761491. Specs and price from detail __NEXT_DATA__. Availability subject to source page.",
        "zh": "来自 PropertyHub 挂牌 5761491。规格与价格取自详情页 JSON；是否可售/可租以来源页为准。",
        "th": "แปลงจากประกาศ PropertyHub 5761491 สเปกและราคาจากหน้าต้นทาง สถานะให้ยึดแหล่งต้นทาง"
      },
      "featured": false,
      "source": "propertyhub",
      "listing_url": "https://propertyhub.in.th/en/listings/1-br-condo-at-ideo-q-sukhumvit-36-near-bts-thong-lor-id-2600359---5761491",
      "source_updated_at": "2026-07-14",
      "collected_at": "2026-07-14",
      "source_captured_at": "2026-07-14",
      "verification_status": "verified",
      "publish_ready": true,
      "latitude": 13.720856043232146,
      "longitude": 100.57638583682271,
      "duplicate_fingerprint": "8e1218c57b3c03f3cf13c8bb072d4439dbbb89e4fa04861b8b59e63ba5a6b29a",
      "source_listing_id": "5761491",
      "normalized_source_url": "https://propertyhub.in.th/en/listings/5761491",
      "source_url_hash": "193595f8404f156471cb0b4116d97deed709be28cbe25818fe36c01ec7c2eb50",
      "soft_match_fingerprint": "44d220ea77cc4e2e6bcc407b4e8ad445d61d3fd28db5522bc06aca2723a9c59c",
      "listing_lifecycle_status": "active",
      "last_seen_at": "2026-07-14",
      "last_verified_at": "2026-07-14"
    },
    {
      "external_ref": "propertyhub-6103237",
      "listing_type": "rent",
      "property_type": "condo",
      "price_thb": 37000,
      "bedrooms": 1,
      "bathrooms": 1,
      "area_sqm": 45,
      "floor_label": "11",
      "building_label": null,
      "project_slug": "ideo-q-sukhumvit-36",
      "developer_slug": "ananda-development",
      "city_slug": "bangkok",
      "district_slug": "khlong-toei",
      "transit_tags": [
        "bts"
      ],
      "title": {
        "en": "Well-Priced 1-BR 45 Sqm At Ideo Q Sukhumvit 36, 400m to BTS Thong Lor (ID 2952509)",
        "zh": "Well-Priced 1-BR 45 Sqm At Ideo Q Sukhumvit 36, 400m to BTS Thong Lor (ID 2952509)",
        "th": "Well-Priced 1-BR 45 Sqm At Ideo Q Sukhumvit 36, 400m to BTS Thong Lor (ID 2952509)"
      },
      "summary": {
        "en": "Rent: 1BR, 45 sq.m., 37,000 THB. Source PropertyHub #6103237.",
        "zh": "出租：1卧，45㎡，37,000 泰铢。来源 PropertyHub #6103237。",
        "th": "เช่า: 1 นอน 45 ตร.ม. ราคา 37,000 บาท (PropertyHub #6103237)"
      },
      "description": {
        "en": "Normalized from PropertyHub listing 6103237. Specs and price from detail __NEXT_DATA__. Availability subject to source page.",
        "zh": "来自 PropertyHub 挂牌 6103237。规格与价格取自详情页 JSON；是否可售/可租以来源页为准。",
        "th": "แปลงจากประกาศ PropertyHub 6103237 สเปกและราคาจากหน้าต้นทาง สถานะให้ยึดแหล่งต้นทาง"
      },
      "featured": false,
      "source": "propertyhub",
      "listing_url": "https://propertyhub.in.th/en/listings/1-br-condo-at-ideo-q-sukhumvit-36-near-bts-thong-lor-id-2952509---6103237",
      "source_updated_at": "2026-07-14",
      "collected_at": "2026-07-14",
      "source_captured_at": "2026-07-14",
      "verification_status": "verified",
      "publish_ready": true,
      "latitude": 13.720856043232146,
      "longitude": 100.57638583682271,
      "duplicate_fingerprint": "645c16a3324986843f1023cfbaf441e6a8102ecbb8a66f221095d8bbb81dd4eb",
      "source_listing_id": "6103237",
      "normalized_source_url": "https://propertyhub.in.th/en/listings/6103237",
      "source_url_hash": "6054950babe2836e02306dde5de71fb1c5c2a99e7846861bb9aebd6325354c89",
      "soft_match_fingerprint": "46d79c7a5817823c0627b3b4542ae50ec85a625d1ac9c4e8dc38c12657eb301a",
      "listing_lifecycle_status": "active",
      "last_seen_at": "2026-07-14",
      "last_verified_at": "2026-07-14"
    },
    {
      "external_ref": "propertyhub-6166463",
      "listing_type": "rent",
      "property_type": "condo",
      "price_thb": 39000,
      "bedrooms": 1,
      "bathrooms": 1,
      "area_sqm": 47,
      "floor_label": "19",
      "building_label": null,
      "project_slug": "ideo-q-sukhumvit-36",
      "developer_slug": "ananda-development",
      "city_slug": "bangkok",
      "district_slug": "khlong-toei",
      "transit_tags": [
        "bts"
      ],
      "title": {
        "en": "1-BR 47 Sqm, 19th-Floor At Ideo Q Sukhumvit 36 near BTS Thong Lor (ID 3008964)",
        "zh": "1-BR 47 Sqm, 19th-Floor At Ideo Q Sukhumvit 36 near BTS Thong Lor (ID 3008964)",
        "th": "1-BR 47 Sqm, 19th-Floor At Ideo Q Sukhumvit 36 near BTS Thong Lor (ID 3008964)"
      },
      "summary": {
        "en": "Rent: 1BR, 47 sq.m., 39,000 THB. Source PropertyHub #6166463.",
        "zh": "出租：1卧，47㎡，39,000 泰铢。来源 PropertyHub #6166463。",
        "th": "เช่า: 1 นอน 47 ตร.ม. ราคา 39,000 บาท (PropertyHub #6166463)"
      },
      "description": {
        "en": "Normalized from PropertyHub listing 6166463. Specs and price from detail __NEXT_DATA__. Availability subject to source page.",
        "zh": "来自 PropertyHub 挂牌 6166463。规格与价格取自详情页 JSON；是否可售/可租以来源页为准。",
        "th": "แปลงจากประกาศ PropertyHub 6166463 สเปกและราคาจากหน้าต้นทาง สถานะให้ยึดแหล่งต้นทาง"
      },
      "featured": false,
      "source": "propertyhub",
      "listing_url": "https://propertyhub.in.th/en/listings/1-br-condo-at-ideo-q-sukhumvit-36-near-bts-thong-lor-id-3008964--a6e9091e---6166463",
      "source_updated_at": "2026-07-14",
      "collected_at": "2026-07-14",
      "source_captured_at": "2026-07-14",
      "verification_status": "verified",
      "publish_ready": true,
      "latitude": 13.720856043232146,
      "longitude": 100.57638583682271,
      "duplicate_fingerprint": "19975452b3f2108fac8b66ab174d775001e4e9474813161ea2b0a68300d2378d",
      "source_listing_id": "6166463",
      "normalized_source_url": "https://propertyhub.in.th/en/listings/6166463",
      "source_url_hash": "c4345970ffc9992b25abf4e07203417df8e7acaf3c0252f69a46102f7cab5e40",
      "soft_match_fingerprint": "a6b32e2e3e1c208be6b996a0c95d75f729f2f834640665c569086b755a8bc3d7",
      "listing_lifecycle_status": "active",
      "last_seen_at": "2026-07-14",
      "last_verified_at": "2026-07-14"
    }
  ]
}
