{
  "city_slug": "bangkok",
  "slug": "thawi-watthana",
  "name": {
    "en": "Thawi Watthana",
    "zh": "塔威瓦他那",
    "th": "ทวีวัฒนา"
  },
  "summary": {
    "en": "Thawi Watthana is one of the 50 districts (khet) of Bangkok, Thailand. Its neighbor, clockwise from north, are Bang Kruai district of Nonthaburi province, Taling Chan, Bang Khae, and Nong Khaem Districts of Bangkok, Sam Phran and Phutthamonthon of Nakhon Pathom province.",
    "zh": "塔威瓦他那（Thawi Watthana）为曼谷大都会管理局下辖的行政区（เขต）。概述依据英文维基百科该区条目公开摘要。",
    "th": "ทวีวัฒนา เป็นเขตการปกครองของกรุงเทพมหานคร สรุปภาพรวมอ้างอิงจากบทคัดย่อสาธารณะของวิกิพีเดียภาษาอังกฤษสำหรับเขตนี้"
  },
  "seo": {
    "title": {
      "en": "Thawi Watthana Bangkok Property | GoThailandHome",
      "zh": "曼谷塔威瓦他那房产 | GoThailandHome",
      "th": "อสังหาฯ ทวีวัฒนา กรุงเทพฯ | GoThailandHome"
    },
    "description": {
      "en": "Browse Thawi Watthana district property pages for Bangkok projects and verified public listings as inventory is imported.",
      "zh": "浏览曼谷塔威瓦他那区域房产页；项目与公开挂牌随真实导入上线。",
      "th": "ดูหน้าอสังหาฯ เขตทวีวัฒนา กรุงเทพฯ โครงการและประกาศจะเพิ่มเมื่อนำเข้าจากแหล่งจริง"
    }
  },
  "publish_ready": true,
  "sources": [
    {
      "type": "wikipedia",
      "name": "Wikipedia — Thawi Watthana district",
      "url": "https://en.wikipedia.org/wiki/Thawi_Watthana_district"
    },
    {
      "type": "wikipedia",
      "name": "Wikipedia — List of districts of Bangkok",
      "url": "https://en.wikipedia.org/wiki/List_of_districts_of_Bangkok"
    },
    {
      "type": "bma",
      "name": "BMA district GIS portal (50 districts overview)",
      "url": "https://district.bangkok.go.th/SEDPortal/50-map-overview/"
    }
  ],
  "locale_status": {
    "en": "complete",
    "zh": "complete",
    "th": "complete"
  },
  "metadata": {
    "district_code": 48,
    "postal_code": "10170",
    "latitude": 13.776,
    "longitude": 100.348,
    "khwaeng_count": 2
  },
  "transportation": [],
  "schools": [
    {
      "name": {
        "en": "Bangkokthonburi University",
        "zh": "Bangkokthonburi University",
        "th": "Bangkokthonburi University"
      },
      "source_url": "https://en.wikipedia.org/wiki/Bangkokthonburi_University"
    },
    {
      "name": {
        "en": "private university",
        "zh": "private university",
        "th": "private university"
      },
      "source_url": "https://en.wikipedia.org/wiki/private_university"
    },
    {
      "name": {
        "en": "Thongsook College",
        "zh": "Thongsook College",
        "th": "Thongsook College"
      },
      "source_url": "https://en.wikipedia.org/wiki/Thongsook_College"
    }
  ],
  "hospitals": [
    {
      "name": {
        "en": "Thonburi Hospital",
        "zh": "Thonburi Hospital",
        "th": "Thonburi Hospital"
      },
      "source_url": "https://en.wikipedia.org/wiki/Thonburi_Hospital"
    },
    {
      "name": {
        "en": "first private hospital",
        "zh": "first private hospital",
        "th": "first private hospital"
      },
      "source_url": "https://en.wikipedia.org/wiki/List_of_hospitals_in_Thailand"
    }
  ],
  "shopping": [
    {
      "name": {
        "en": "Thonburi Market",
        "zh": "Thonburi Market",
        "th": "Thonburi Market"
      },
      "source_url": "https://en.wikipedia.org/wiki/Thonburi_Market"
    },
    {
      "name": {
        "en": "night market",
        "zh": "night market",
        "th": "night market"
      },
      "source_url": "https://en.wikipedia.org/wiki/night_market"
    }
  ],
  "investment_summary": {
    "en": "Thawi Watthana is an administrative district of Bangkok. This package does not include rental yields, price indices, or inventory counts — those require separately sourced market data.",
    "zh": "塔威瓦他那为曼谷行政区。本数据包不含租金收益率、价格指数或库存数量——该类指标需另行引用可核对的市场来源。",
    "th": "ทวีวัฒนาเป็นเขตการปกครองของกรุงเทพฯ แพ็กเกจนี้ไม่มีตัวเลขผลตอบแทนค่าเช่า ดัชนีราคา หรือจำนวนสินค้าคงคลัง — ต้องอ้างอิงแหล่งข้อมูลตลาดที่ตรวจสอบได้แยกต่างหาก"
  },
  "nearby_projects": [],
  "parks": [],
  "field_evidence": {
    "bts": {
      "field": "bts",
      "evidence_class": "OFFICIAL_ABSENCE",
      "provenance": {
        "source_type": "wikipedia_transit_line_map",
        "url": "https://en.wikipedia.org/wiki/BTS_Skytrain"
      },
      "verified_at": "2026-07-16",
      "present": false,
      "absence_verified": true
    },
    "mrt": {
      "field": "mrt",
      "evidence_class": "OFFICIAL_ABSENCE",
      "provenance": {
        "source_type": "wikipedia_transit_line_map",
        "url": "https://en.wikipedia.org/wiki/Blue_Line_(Bangkok)"
      },
      "verified_at": "2026-07-16",
      "present": false,
      "absence_verified": true
    },
    "schools": {
      "field": "schools",
      "evidence_class": "OFFICIAL",
      "provenance": {
        "source_type": "wikipedia_district_places",
        "url": "https://en.wikipedia.org/wiki/Thawi_Watthana_district"
      },
      "verified_at": "2026-07-16",
      "present": true,
      "absence_verified": false
    },
    "hospitals": {
      "field": "hospitals",
      "evidence_class": "OFFICIAL",
      "provenance": {
        "source_type": "wikipedia_district_places",
        "url": "https://en.wikipedia.org/wiki/Thawi_Watthana_district"
      },
      "verified_at": "2026-07-16",
      "present": true,
      "absence_verified": false
    },
    "shopping": {
      "field": "shopping",
      "evidence_class": "OFFICIAL",
      "provenance": {
        "source_type": "wikipedia_district_places",
        "url": "https://en.wikipedia.org/wiki/Thawi_Watthana_district"
      },
      "verified_at": "2026-07-16",
      "present": true,
      "absence_verified": false
    },
    "parks": {
      "field": "parks",
      "evidence_class": "UNVERIFIED",
      "provenance": {
        "source_type": "wikipedia_district_places",
        "url": "https://en.wikipedia.org/wiki/Thawi_Watthana_district"
      },
      "verified_at": "2026-07-16",
      "present": false,
      "absence_verified": false
    },
    "overview": {
      "field": "overview",
      "evidence_class": "OFFICIAL",
      "provenance": {
        "source_type": "wikipedia_or_bma",
        "url": "https://en.wikipedia.org/wiki/Thawi_Watthana_district"
      },
      "verified_at": "2026-07-16",
      "present": true,
      "absence_verified": false
    },
    "map": {
      "field": "map",
      "evidence_class": "OFFICIAL",
      "provenance": {
        "source_type": "package_centroid_coordinates",
        "url": "https://www.google.com/maps?q=13.776,100.348"
      },
      "verified_at": "2026-07-16",
      "present": true,
      "absence_verified": false
    },
    "lifestyle": {
      "field": "lifestyle",
      "evidence_class": "OFFICIAL",
      "provenance": {
        "source_type": "wikipedia_district_page",
        "url": "https://en.wikipedia.org/wiki/Thawi_Watthana_district"
      },
      "verified_at": "2026-07-16",
      "present": true,
      "absence_verified": false
    },
    "office_areas": {
      "field": "office_areas",
      "evidence_class": "UNVERIFIED",
      "provenance": {
        "source_type": "wikipedia_district_page",
        "url": "https://en.wikipedia.org/wiki/Thawi_Watthana_district"
      },
      "verified_at": "2026-07-16",
      "present": false,
      "absence_verified": false
    }
  },
  "district_master": {
    "phase": "10-sprint-5b",
    "verified_at": "2026-07-16",
    "rule": "wiki_places_harvest_named_pois_plus_extract_lifestyle"
  },
  "overview_source": {
    "type": "wikipedia_rest_summary",
    "url": "https://en.wikipedia.org/wiki/Thawi_Watthana_district",
    "verified_at": "2026-07-16"
  },
  "google_maps_url": "https://www.google.com/maps?q=13.776,100.348",
  "map": {
    "latitude": 13.776,
    "longitude": 100.348,
    "google_maps_url": "https://www.google.com/maps?q=13.776,100.348",
    "source": "district_package_centroid",
    "verified_at": "2026-07-16"
  },
  "lifestyle": {
    "en": "Thawi Watthana is one of the 50 districts (khet) of Bangkok, Thailand.",
    "zh": "塔威瓦他那（Thawi Watthana）概述依据英文维基百科该区条目公开摘要首句。",
    "th": "ทวีวัฒนา สรุปไลฟ์สไตล์/บริบทจากประโยคแรกของบทคัดย่อวิกิพีเดียภาษาอังกฤษสำหรับเขตนี้",
    "source_url": "https://en.wikipedia.org/wiki/Thawi_Watthana_district",
    "verified_at": "2026-07-16",
    "evidence_note": "wikipedia_extract_first_sentence"
  }
}
